pressoir_cli/__init__.py
pressoir_cli/__main__.py
pressoir_cli/additionals.py
pressoir_cli/cli.py
pressoir_cli/generator.py
pressoir_cli/indexes.py
pressoir_cli/models.py
pressoir_cli/project.toml
pressoir_cli/sidenotes.py
pressoir_cli/statics.py
pressoir_cli/utils.py
pressoir_cli/docs/pressoir/book.toml
pressoir_cli/docs/pressoir/static/css/custom.css
pressoir_cli/docs/pressoir/static/css/fonts.css
pressoir_cli/docs/pressoir/static/css/vars.css
pressoir_cli/docs/pressoir/static/fonts/averialibre-bold.woff
pressoir_cli/docs/pressoir/static/fonts/averialibre-bold.woff2
pressoir_cli/docs/pressoir/static/fonts/averiaseriflibre-light.woff
pressoir_cli/docs/pressoir/static/fonts/averiaseriflibre-light.woff2
pressoir_cli/docs/pressoir/static/img/pressoir-logo.png
pressoir_cli/docs/pressoir/static/svg/minus.svg
pressoir_cli/docs/pressoir/static/svg/parcours-numeriques.png
pressoir_cli/docs/pressoir/static/svg/personnalite.svg
pressoir_cli/docs/pressoir/static/svg/plus.svg
pressoir_cli/docs/pressoir/static/svg/pum-logo-couleur.svg
pressoir_cli/docs/pressoir/static/svg/pum-logo-noir.svg
pressoir_cli/docs/pressoir/static/svg/quote.svg
pressoir_cli/docs/textes/bibliographie/bibliographie.bib
pressoir_cli/docs/textes/bibliographie/bibliographie.md
pressoir_cli/docs/textes/bibliographie/bibliographie.yaml
pressoir_cli/docs/textes/chapitre1/additionnels.md
pressoir_cli/docs/textes/chapitre1/chapitre1.bib
pressoir_cli/docs/textes/chapitre1/chapitre1.md
pressoir_cli/docs/textes/chapitre1/chapitre1.yaml
pressoir_cli/docs/textes/chapitre2/additionnels.md
pressoir_cli/docs/textes/chapitre2/chapitre2.bib
pressoir_cli/docs/textes/chapitre2/chapitre2.md
pressoir_cli/docs/textes/chapitre2/chapitre2.yaml
pressoir_cli/docs/textes/chapitre3/additionnels.md
pressoir_cli/docs/textes/chapitre3/chapitre3.bib
pressoir_cli/docs/textes/chapitre3/chapitre3.md
pressoir_cli/docs/textes/chapitre3/chapitre3.yaml
pressoir_cli/docs/textes/chapitre4/additionnels.md
pressoir_cli-2.2.5.dist-info/METADATA
pressoir_cli-2.2.5.dist-info/WHEEL
pressoir_cli-2.2.5.dist-info/entry_points.txt
pressoir_cli-2.2.5.dist-info/licenses/LICENSE
pressoir_cli-2.2.5.dist-info/RECORD
