Metadata-Version: 2.3
Name: pressoir-cli
Version: 2.2.5
Requires-Python: >=3.8
Requires-Dist: dataclass-wizard
Requires-Dist: jinja2
Requires-Dist: minicli
Requires-Dist: progressist
Requires-Dist: pypandoc
Requires-Dist: python-slugify
Requires-Dist: pyyaml
Requires-Dist: selectolax
Requires-Dist: tomli>=1.1.0; python_version < '3.11'
Requires-Dist: unidecode
Provides-Extra: dev
Requires-Dist: black; extra == 'dev'
Requires-Dist: cogapp; extra == 'dev'
Requires-Dist: hatch; extra == 'dev'
Requires-Dist: isort; extra == 'dev'
Requires-Dist: pytest; extra == 'dev'
Requires-Dist: ruff; extra == 'dev'
